ckanext_emailasusername-1.2.1-py3.11-nspkg.pth
ckanext/emailasusername/__init__.py
ckanext/emailasusername/authenticator.py
ckanext/emailasusername/blueprint.py
ckanext/emailasusername/helpers.py
ckanext/emailasusername/interfaces.py
ckanext/emailasusername/logic.py
ckanext/emailasusername/plugin.py
ckanext/emailasusername/i18n/fr/LC_MESSAGES/ckanext-emailasusername.mo
ckanext/emailasusername/i18n/pt_PT/LC_MESSAGES/ckanext-emailasusername.mo
ckanext/emailasusername/templates/user/new_user_form.html
ckanext/emailasusername/templates/user/request_reset.html
ckanext/emailasusername/templates/user/snippets/custom_username_css.html
ckanext/emailasusername/templates/user/snippets/login_form.html
ckanext/emailasusername/tests/__init__.py
ckanext/emailasusername/tests/test_authenticator.py
ckanext/emailasusername/tests/test_blueprint.py
ckanext/emailasusername/tests/test_logic.py
ckanext/emailasusername/tests/test_plugin.py
ckanext_emailasusername-1.2.1.dist-info/LICENSE
ckanext_emailasusername-1.2.1.dist-info/METADATA
ckanext_emailasusername-1.2.1.dist-info/WHEEL
ckanext_emailasusername-1.2.1.dist-info/entry_points.txt
ckanext_emailasusername-1.2.1.dist-info/namespace_packages.txt
ckanext_emailasusername-1.2.1.dist-info/top_level.txt
ckanext_emailasusername-1.2.1.dist-info/RECORD
