Metadata-Version: 2.1
Name: ckanext-emailasusername
Version: 1.2.1
Summary: Allows users to login with email as well as username.
Home-page: https://github.com/jonathansberry/ckanext-emailasusername
Author: Jonathan Berry
Author-email: jonathan@fjelltopp.org
License: AGPL
Keywords: CKAN ADR Email Username Login Register Password
Classifier: Development Status :: 4 - Beta
Classifier: License :: OSI Approved :: GNU Affero General Public License v3 or later (AGPLv3+)
Requires-Python: >=3.6
License-File: LICENSE
